example/__init__.py
example/math.py
Hytera-1.0.0.dist-info/LICENSE
Hytera-1.0.0.dist-info/METADATA
Hytera-1.0.0.dist-info/WHEEL
Hytera-1.0.0.dist-info/top_level.txt
Hytera-1.0.0.dist-info/RECORD
