Metadata-Version: 2.1
Name: Hytera
Version: 1.0.0
Summary: 海能达专用python工具包
Home-page: https://github.com/JustDoPython/justdopython.github.io
Author: 王若蒙
Author-email: wangrm40@chinaunicom.cn
License: UNKNOWN
Platform: UNKNOWN
Classifier: Programming Language :: Python :: 3
Classifier: License :: OSI Approved :: MIT License
Classifier: Operating System :: OS Independent
